vimania_todos/__init__.py
vimania_todos/environment.py
vimania_todos/exception.py
vimania_todos/db/__init__.py
vimania_todos/db/dal.py
vimania_todos/helper/__init__.py
vimania_todos/helper/helper.py
vimania_todos/helper/position.py
vimania_todos/todos/__init__.py
vimania_todos/todos/cli.py
vimania_todos/todos/handle_buffer.py
vimania_todos/todos/handler.py
vimania_todos/todos/model.py
vimania_todos/todos/pattern.py
vimania_todos/vim_/__init__.py
vimania_todos/vim_/compatibility.py
vimania_todos/vim_/vim_helper.py
vimania_todos/vim_/vimania_manager.py
vimania_todos-1.3.3.dist-info/LICENSE
vimania_todos-1.3.3.dist-info/METADATA
vimania_todos-1.3.3.dist-info/WHEEL
vimania_todos-1.3.3.dist-info/entry_points.txt
vimania_todos-1.3.3.dist-info/top_level.txt
vimania_todos-1.3.3.dist-info/RECORD
