Metadata-Version: 2.1
Name: vimania-todos
Version: 1.3.3
Summary: "todo manager with VIM"
Home-page: https://github.com/sysid/vimania-todos
Author: sysid
Author-email: sysid@gmx.de
Classifier: Development Status :: 4 - Beta
Classifier: Intended Audience :: Developers
Classifier: License :: OSI Approved :: GNU General Public License v3 (GPLv3)
Classifier: Operating System :: OS Independent
Classifier: Topic :: Utilities
Classifier: Programming Language :: Python :: 3
Classifier: Programming Language :: Python :: 3.9
Requires-Python: >=3.9
License-File: LICENSE
Requires-Dist: bs4
Requires-Dist: SQLAlchemy
Requires-Dist: typer
Requires-Dist: pydantic[dotenv]
Requires-Dist: requests
Requires-Dist: lxml
Requires-Dist: pure-sql
